avrex/__init__.py
avrex/api.py
avrex/cli.py
avrex-0.2.0.dist-info/LICENSE
avrex-0.2.0.dist-info/METADATA
avrex-0.2.0.dist-info/WHEEL
avrex-0.2.0.dist-info/entry_points.txt
avrex-0.2.0.dist-info/top_level.txt
avrex-0.2.0.dist-info/RECORD
