Metadata-Version: 2.1
Name: avrex
Version: 0.2.0
Summary: AssociationVoice reports exporter
Home-page: https://github.com/carsonyl/avrex
Author: Carson Lam
Author-email: 46059+carsonyl@users.noreply.github.com
License: Apache License 2.0
Platform: UNKNOWN
Classifier: Programming Language :: Python :: 3
Classifier: Programming Language :: Python :: 3.7
Classifier: Programming Language :: Python :: 3.8
Classifier: Programming Language :: Python :: 3.9
Classifier: Programming Language :: Python :: 3 :: Only
Classifier: License :: OSI Approved :: Apache Software License
Classifier: Operating System :: OS Independent
Requires-Python: >=3.7
Requires-Dist: MechanicalSoup (>=1.0.0)
Requires-Dist: python-dotenv
Requires-Dist: click
Provides-Extra: dev
Requires-Dist: pytest ; extra == 'dev'
Requires-Dist: pytest-vcr ; extra == 'dev'
Requires-Dist: wheel ; extra == 'dev'
